nbdb/__init__.py
nbdb/py.typed
nbdb/storage.py
nonbloat_db-0.1.4.dist-info/LICENSE
nonbloat_db-0.1.4.dist-info/METADATA
nonbloat_db-0.1.4.dist-info/WHEEL
nonbloat_db-0.1.4.dist-info/RECORD
